Workbook

Sheet Históricos
B2: Cliente: | C2: ISSSTE
B3: Proyecto: | C3: Re Portabilidad
B6: Información histórica de referencia
B7: Indique el nombre del proyecto o proyectos de referencia revisados
B8: Nombre del proyecto | F8: Aspectos considerados
B9: Portabilidad | F9: Dominio de la aplicación: portabilidad de derechos pensionarios (integración ISSSTE-IMSS). Dominio de la tecnología: Genero BDL/4GL sobre GAS, Informix. Complejidad: media-alta (7 servicios web externos, catálogo de rechazo de 59 claves). Conocimiento del equipo: alto (mismo equipo con experiencia previa en SIPE-AV).

Sheet 1.-Factores técnicos
E2: Determinar el valor que caracteriza a cada factor de 0 a 5.
B3: Factor técnico | D3: Peso | E3: Magnitud relativa (Ingrese 0-5) | F3: Descripción
B4: 1 | C4: Sistema Distribuido Requerido | D4: 2 | E4: 1 | F4: La arquitectura de la solución puede ser centralizada o de un solo usuario, o puede ser distribuida (como una solución de "n" niveles) o multiusuario. Los números más altos representan una arquitectura más compleja.
B5: 2 | C5: El tiempo de respuesta es importante | D5: 2 | E5: 1 | F5: ¿La rapidez de respuesta de los usuarios es un factor importante? (y no trivial). Por ejemplo, si se espera que la carga del servidor sea muy baja, esto puede ser un factor trivial. Los números más altos representan una importancia creciente del tiempo de respuesta (un motor de búsqueda tendría un número alto, un agregador diario de noticias tendría un número bajo).
B6: 3 | C6: Eficiencia del usuario final | D6: 2 | E6: 1 | F6: ¿La aplicación se está desarrollando para optimizar la eficiencia del usuario o solo la capacidad? Los números más altos representan proyectos que dependen más de la aplicación para mejorar la eficiencia del usuario.
B7: 4 | C7: Procesamiento interno complejo requerido | D7: 2 | E7: 1 | F7: ¿Hay mucho trabajo algorítmico difícil de hacer y probar? Los algoritmos complejos (nivelación de recursos, análisis de sistemas en el dominio del tiempo, cubos OLAP) tienen números más altos. Las consultas simples a la base de datos tendrían números bajos.
B8: 5 | C8: El código reutilizable debe ser un foco | D8: 3 | E8: 2 | F8: ¿La reutilización de código pesado es un objetivo o una meta? La reutilización de código reduce la cantidad de esfuerzo necesario para implementar un proyecto. También reduce la cantidad de tiempo necesario para depurar un proyecto. Una función de biblioteca compartida se puede reutilizar varias veces y arreglar el código en un solo lugar puede resolver varios errores. Cuanto mayor sea el nivel de reutilización, menor será el número.
B9: 6 | C9: Fácil instalación | D9: 1 | E9: 5 | F9: ¿La facilidad de instalación para los usuarios finales es un factor clave? Cuanto mayor sea el nivel de competencia de los usuarios, menor será el número.
B10: 7 | C10: Usabilidad | D10: 1 | E10: 5 | F10: ¿Es la facilidad de uso un criterio principal para la aceptación? Cuanto mayor sea la importancia de la usabilidad, mayor será el número.
B11: 8 | C11: Soporte multiplataforma | D11: 5 | E11: 5 | F11: ¿Se requiere soporte multiplataforma? Cuantas más plataformas deban ser compatibles (esto podría ser versiones de navegador, dispositivos móviles, etc. o Windows/OSX/Unix), mayor será el valor.
B12: 9 | C12: Fácil de cambiar | D12: 3 | E12: 2 | F12: ¿El cliente requiere la capacidad de cambiar o personalizar la aplicación en el futuro? Cuantos más cambios/personalizaciones se requieran en el futuro, mayor será el valor.
B13: 10 | C13: Altamente concurrente | D13: 5 | E13: 3 | F13: ¿Tendrá que abordar el bloqueo de la base de datos y otros problemas de simultaneidad? Cuanta más atención deba dedicar a resolver conflictos en los datos o la aplicación, mayor será el valor.
B14: 11 | C14: Seguridad personalizada | D14: 2 | E14: 2 | F14: ¿Se pueden aprovechar las soluciones de seguridad existentes o se debe desarrollar un código personalizado? Cuanto más trabajo de seguridad personalizado tenga que hacer (nivel de campo, nivel de página o seguridad basada en funciones, por ejemplo), mayor será el valor.
B15: 12 | C15: Dependencia del código de terceros | D15: 3 | E15: 3 | F15: ¿La aplicación requerirá el uso de controles o bibliotecas de terceros? Al igual que el código reutilizable, el código de terceros puede reducir el esfuerzo necesario para implementar una solución. Cuanto más código de terceros (y más fiable sea el código de terceros), menor será el número.
B16: 13 | C16: Entrenamiento de usuario | D16: 2 | E16: 2 | F16: ¿Cuánta capacitación del usuario se requiere? ¿La aplicación es compleja o admite actividades complejas? Cuanto más tarden los usuarios en cruzar el umbral de succión (lograr un nivel de dominio del producto), mayor será el valor.
B17: TCF calculados | E17: {=0.6+(SUM(D4:D16*E4:E16)/100)} -> 1.47

Sheet 2.-Factores ambientales
E2: Determinar el valor que caracteriza a cada factor de 0 a 5.
B3: Factor ambiental | D3: Peso | E3: Magnitud relativa (Ingrese 0-5) | F3: Descripción
B4: 1 | C4: Familiaridad con el proyecto | D4: 3 | E4: 3 | F4: ¿Cuánta experiencia tiene su equipo trabajando en este dominio? El dominio del proyecto será un reflejo de lo que el software pretende lograr, no el lenguaje de implementación. En otras palabras, para un sistema de compensación de seguros escrito en java, te importa la experiencia del equipo en el espacio de compensación de seguros, no cuánto java han escrito. Los niveles más altos de experiencia obtienen un número más alto.
B5: 2 | C5: Experiencia de aplicación | D5: 3 | E5: 2 | F5: ¿Cuánta experiencia tiene su equipo con la aplicación?. Esto solo será relevante cuando se realicen cambios en una aplicación existente. Los números más altos representan más experiencia. Para una nueva aplicación, la experiencia de todos será 0.
B6: 3 | C6: Experiencia en programación orientada a objetos | D6: 3 | E6: 2 | F6: ¿Cuánta experiencia tiene tu equipo en OO? Puede ser fácil olvidar que muchas personas no tienen experiencia en programación orientada a objetos si está acostumbrado a tenerla. Un proyecto centrado en el usuario o basado en casos de uso tendrá una estructura inherentemente OO en la implementación. Los números más altos representan más experiencia OO.
B7: 4 | C7: Capacidad del analista principal | D7: 3 | E7: 2 | F7: ¿Qué tan conocedora y capaz es la persona responsable de los requisitos? Los malos requisitos son el asesino número uno de los proyectos: el Grupo Standish informa que del 40% al 60% de los defectos provienen de malos requisitos. Los números más altos representan una mayor habilidad y conocimiento.
B8: 5 | C8: Motivación | D8: 3 | E8: 3 | F8: ¿Qué tan motivado está tu equipo? Los números más altos representan más motivación
B9: 6 | C9: Estabilidad de los requisitos | D9: 1 | E9: 1 | F9: ¿Qué tanto nos desestabiliza el cambio?, Los cambios en los requisitos pueden causar aumentos en el trabajo. La forma de evitar esto es planificando el cambio e instituyendo un sistema de cronometraje para administrar esos cambios. Algunos retrabajos serán inevitables. Los números más altos representan más cambios (o un sistema menos efectivo para gestionar el cambio).
B10: 7 | C10: Personal a tiempo parcial | D10: 0 | E10: 0 | F10: ¿Hay personal de manera parcial en el proyecto?, se involucran en varios proyectos al mismo tiempo, al tener una persona en tiempo parcial el número es mayor a 0 (cero). Tenga en cuenta que el multiplicador para este número es negativo. Los números más altos reflejan a los miembros del equipo que son a tiempo parcial, consultores externos y desarrolladores que dividen su tiempo en proyectos. El cambio de contexto y otros factores intangibles hacen que estos miembros del equipo sean menos eficientes.
B11: 8 | C11: Lenguaje de programación difícil | D11: 0 | E11: 0 | F11: Este multiplicador también es negativo. Los idiomas más difíciles representan números más altos. Creemos que la dificultad está en el ojo del be-coder (gemido). Java puede ser difícil para un programador de Fortran. Piénsalo en términos de dificultad para tu equipo, no de dificultad abstracta.
B12: EF Calculados | E12: {=1.4-(0.03*SUM(D4:D11*E4:E11))} -> 0.29

Sheet 3.-Casos de uso
B2: Puntos de caso de uso sin ajustar | D2: Peso | E2: Número de casos de uso | F2: Descripción
B3: 1 | C3: Simple | D3: 5 | E3: 5 | F3: Caso de uso simple: Hasta 3 transacciones.
B4: 2 | C4: Promedio | D4: 10 | E4: {=SUM(IF(C$9:C$17=C4,1,0)*IF(E$9:F$17<>"",1,0))} -> 2 | F4: Caso de uso promedio: de 4 a 7 transacciones.
B5: 3 | C5: Complejo | D5: 15 | E5: 1 | F5: Caso de uso complejo: más de 7 transacciones.
B6: UUCP calculados | E6: {=SUM(D3:D5*E3:E5)} -> 60
B9: Casos de uso individual | D9: Peso | E9: Nombre de caso de uso
B10: 1 | C10: Simple | D10: =SUMIF(C$3:C$5,C10,D$3:D$5) -> 5 | E10: Busqueda y recuperación de derechohabiente
B11: =B10+1 -> 2 | C11: Simple | D11: =SUMIF(C$3:C$5,C11,D$3:D$5) -> 5 | E11: Consulta del servicio WS1-IMSS-Consulta de estatus derechoahbiente
B12: =B11+1 -> 3 | C12: Simple | D12: =SUMIF(C$3:C$5,C12,D$3:D$5) -> 5 | E12: Consulta del servicio WS2-PROCESAR-consulta estatus
B13: =B12+1 -> 4 | C13: Promedio | D13: =SUMIF(C$3:C$5,C13,D$3:D$5) -> 10 | E13: Consulta del servicio WS3-IMSS-Consulta de periodos portables
B14: =B13+1 -> 5 | C14: Simple | D14: =SUMIF(C$3:C$5,C14,D$3:D$5) -> 5 | E14: Consulta del servicio WS4-PROCESAR-insercion
B15: =B14+1 -> 6 | C15: Simple | D15: =SUMIF(C$3:C$5,C15,D$3:D$5) -> 5 | E15: Consulta del servicio WS5-PROCESAR-cancelacion
B16: =B15+1 -> 7 | C16: Promedio | D16: =SUMIF(C$3:C$5,C16,D$3:D$5) -> 10 | E16: Consulta del servicio WS6-IMSS-Conclusion Portabilidad
B17: =B16+1 -> 8 | C17: Complejo | D17: =SUMIF(C$3:C$5,C17,D$3:D$5) -> 15 | E17: Consulta del servicio WS7-ISSSTE-Beneficio Pensionario

Sheet 4.-Actores
B2: Listado de actores | D2: Multiplicador | E2: Número de actores | F2: Descripción
B3: 1 | C3: Simple | D3: 2 | E3: 7 | F3: Los actores simples son otro sistema que se comunican con el software a través de una API predefinida. Una API podría exponerse a través de una dll, o como REST, SOAP o cualquier API de servicio web o llamada a procedimiento remoto (RPC). El elemento clave es que está exponiendo la interacción con su software a través de un mecanismo específico y bien definido.
B4: 2 | C4: Promedio | D4: 2 | E4: 0 | F4: Los actores promedio son otro sistema interactuando a través de un protocolo (ej. TCP/IP) o una persona interactuando a través de una interfaz en modo texto.
B5: 3 | C5: Complejo | D5: 3 | E5: 1 | F5: La definición original de actores complejos especifica que los usuarios que interactúan con el software a través de una interfaz gráfica de usuario son actores complejos. Si bien eso es cierto, la misma clasificación debería aplicarse a los usuarios que interactúan con el sistema de manera impredecible. Una interfaz AJAX que expone más de la aplicación subyacente (y almacenes de datos) de lo que estaría disponible a través de un protocolo rígido podría introducir una complejidad similar.
B6: AW Calculado | E6: {=SUM(D3:D5*E3:E5)} -> 17
B9: Actor | D9: Peso | E9: Nombre del actor
B10: 1 | C10: Simple | D10: =SUMIF(C$3:C$5,C10,D$3:D$5) -> 2 | E10: Operación interna BDUD
B11: =B10+1 -> 2 | C11: Simple | D11: =SUMIF(C$3:C$5,C11,D$3:D$5) -> 2 | E11: WS1-IMSS-Consulta de estatus de derechoahbiente
B12: =B11+1 -> 3 | C12: Simple | D12: =SUMIF(C$3:C$5,C12,D$3:D$5) -> 2 | E12: WS2-PROCESAR-Consulta
B13: =B12+1 -> 4 | C13: Simple | D13: =SUMIF(C$3:C$5,C13,D$3:D$5) -> 2 | E13: WS3-IMSS-Consulta de Periodos
B14: =B13+1 -> 5 | C14: Simple | D14: =SUMIF(C$3:C$5,C14,D$3:D$5) -> 2 | E14: WS4-PROCESAR-Insercion
B15: =B14+1 -> 6 | C15: Simple | D15: =SUMIF(C$3:C$5,C15,D$3:D$5) -> 2 | E15: WS5-Cancelación
B16: =B15+1 -> 7 | C16: Simple | D16: =SUMIF(C$3:C$5,C16,D$3:D$5) -> 2 | E16: WS6-Aviso Conculsion Portabilidad
B17: =B16+1 -> 8 | C17: Complejo | D17: =SUMIF(C$3:C$5,C17,D$3:D$5) -> 3 | E17: WS7-Consulta de Beneficio Pensionario
B18: =B17+1 -> 9
B19: =B18+1 -> 10 | G19: Nota: si no escribes el "nombre del actor" no se agregarán datos a "número de actores"

Sheet 5.-Resumen estimación de tamaño
B2: Cálculos de otras tablas
B3: TCF | D3: Factor de complejidad técnica | E3: ='1.-Factores técnicos'!E17 -> 1.47
B4: EF | D4: Factor ambiental | E4: ='2.-Factores ambientales'!E12 -> 0.29
B5: UUCP | D5: Puntos de caso de uso no ajustados | E5: ='3.-Casos de uso'!E6 -> 60
B6: AW | D6: Ponderación de actores | E6: ='4.-Actores'!E6 -> 17
B7: Cálculo de puntos de caso de uso
B8: UCP | D8: Puntos de caso de uso | E8: =(E5+E6)*E3*E4 -> 32.8251
B9: Cálculo del esfuerzo estimado
B10: Relación | D10: Horas de esfuerzo por punto de caso de uso | E10: 24
B12: Horas de esfuerzo | E12: =E8*E10 -> 787.8024

Sheet 6.-Estimación esfuerzo y costo
A2: Desglose de horas por actividad
A3: Actividades | D3: Horas | E3: % | F3: Días hombre
A4: Análisis | D4: =D6*E4 -> 78.78024 | E4: 0.1 | F4: =D4/$C12 -> 9.84753
A5: Diseño | D5: =D6*E5 -> 157.56048 | E5: 0.2 | F5: =D5/$C12 -> 19.69506
A6: Construcción | D6: ='5.-Resumen estimación de tamaño'!E12 -> 787.8024 | E6: 0.6 | F6: =D6/$C12 -> 98.4753
A7: Pruebas | D7: =D6*E7 -> 78.78024 | E7: 0.1 | F7: =D7/$C12 -> 9.84753
A9: Total | D9: =SUM(D4:D7) -> 1102.9234 | E9: =SUM(E4:E7) -> 1 | F9: =SUM(F4:F7) -> 137.86542
A11: DPM | C11: Horas efectivas de trabajo | E11: Días totales (red) | G11: Plazo en meses
A12: 21.5 | C12: 8 | E12: =ROUNDUP(F9,0) -> 138 | G12: =ROUNDUP((F9/A12),0) -> 7
A14: Costos
A15: Rol | C15: Costo por mes
A16: Líder de proyecto
A17: Líder técnico
A18: Analista
A19: Arquitecto
A20: Desarrollador | C20: 40000
A21: Tester
A22: Total | C22: =SUM(C16:C21)*G12 -> 280000
A24: Otros conceptos
A25: Conceptos | D25: Costo
A26: Horas extra | D26: 0
A27: Licencias | D27: 0
A28: Formación | D28: 0
A29: Consumibles | D29: 0
A31: Total | D31: =SUM(D26:D30) -> 0
B33: Presupuesto total | D33: =C22+D31 -> 280000
B36: Análisis | D36: Todos los costos ya fueron proveidos con respaldo contractual tanto con el cliente como con la dirección de Four Js, el unico egreso que se vislumbra es el sueldo del personal asignado al proyecto.
