Workbook

Sheet Global
B1: Presupuesto Global "Four Js"
B5: Descripción | C5: Monto (USD) | D5: % del total
B6: Departamento de Desarrollo de Sistemas | C6: 472500 | D6: 0.63
B7: Departamento Administrativo | C7: 150000 | D7: 0.2
B8: Gastos Operativos Generales | C8: 52500 | D8: 0.07
B9: Reserva Estratégica / Contingencias | C9: 75000 | D9: 0.1
C10: =SUM(C6:C9) -> 750000 | D10: 1
A30: Fecha | B30: Descripción | C30: Versión | D30: Autor
A31: 45950 | B31: Generación del documento. | C31: 1.0 | D31: Carlos Quintero N.

Sheet Organizacional
B1: Presupuesto Organizacional "Four Js"
C5: Puesto | D5: Monto (USD) | E5: % del depto. | F5: Descripción
C6: VP Latin America Sales & Marketing | D6: =Global!C$6*Organizacional!E6 -> 37800 | E6: 0.08 | F6: Dirección estratégica y comercial
C7: Process Manager | D7: =Global!C$6*Organizacional!E7 -> 33075 | E7: 0.07 | F7: Gestión de procesos y mejora continua
C8: Support Manager | D8: =Global!C$6*Organizacional!E8 -> 37800 | E8: 0.08 | F8: Coordinación del soporte técnico
C9: Quality Auditor | D9: =Global!C$6*Organizacional!E9 -> 33075 | E9: 0.07 | F9: Auditorías de calidad y control interno
C10: Customer Support & Training | D10: =Global!C$6*Organizacional!E10 -> 37800 | E10: 0.08 | F10: Soporte y capacitación a clientes
C11: Technical Leader | D11: =Global!C$6*Organizacional!E11 -> 37800 | E11: 0.08 | F11: Dirección técnica y revisión de arquitectura
C12: Consultant | D12: =Global!C$6*Organizacional!E12 -> 28350 | E12: 0.06 | F12: Consultoría especializada
C13: Support Engineer | D13: =Global!C$6*Organizacional!E13 -> 28350 | E13: 0.06 | F13: Atención técnica postventa
C14: Systems Engineer | D14: =Global!C$6*Organizacional!E14 -> 33075 | E14: 0.07 | F14: Administración de entornos y servidores
C15: Software Analyst | D15: =Global!C$6*Organizacional!E15 -> 33075 | E15: 0.07 | F15: Análisis funcional y requerimientos
C16: Software Architect | D16: =Global!C$6*Organizacional!E16 -> 33075 | E16: 0.07 | F16: Diseño de estructuras y frameworks
C17: Software Designer | D17: =Global!C$6*Organizacional!E17 -> 28350 | E17: 0.06 | F17: Diseño de interfaz y usabilidad
... C19: Software Tester | D19: =Global!C$6*Organizacional!E19 -> 18900 | E19: 0.04 | F19: Pruebas de calidad y validación final
D20: =SUM(D6:D19) -> 472500 | E20: =SUM(E6:E19) -> 1

Sheet Administrativo
B1: Presupuesto Administrativo "Four Js"
B5: Puesto | C5: Monto (USD) | D5: % del depto. | E5: Descripción
B6: Contador | C6: =Global!C$7*Administrativo!D6 -> 37500 | D6: 0.25 | E6: Contabilidad general y fiscal
B7: Seguro Social | C7: =Global!C$7*Administrativo!D7 -> 37500 | D7: 0.25 | E7: Aportaciones y cumplimiento legal
B8: Recursos Humanos | C8: =Global!C$7*Administrativo!D8 -> 37500 | D8: 0.25 | E8: Reclutamiento y clima laboral
B9: Contraloría | C9: =Global!C$7*Administrativo!D9 -> 37500 | D9: 0.25 | E9: Supervisión financiera y control presupuestal
C10: =SUM(C6:C9) -> 150000 | D10: =SUM(D6:D9) -> 1

Sheet Gastos Operativos Generales
B1: Presupuesto Gastos Operativos Generales "Four Js"
B5: Concepto | C5: Monto (USD) | D5: % del depto. | E5: Descripción
B6: Renta de oficinas | C6: =Global!C$8*'Gastos Operativos Generales'!D6 -> 18900 | D6: 0.36 | E6: Espacio físico o coworking
B7: Servicios básicos (luz, agua, internet, limpieza) | C7: =Global!C$8*'Gastos Operativos Generales'!D7 -> 10500 | D7: 0.2 | E7: Mantenimiento operativo general
B8: Equipos y mantenimiento TI | C8: =Global!C$8*'Gastos Operativos Generales'!D8 -> 7350 | D8: 0.14 | E8: Renovación y soporte de equipos
B9: Viajes / representación | C9: =Global!C$8*'Gastos Operativos Generales'!D9 -> 7350 | D9: 0.14 | E9: Reuniones con clientes y partners
B10: Comunicaciones y marketing digital | C10: =Global!C$8*'Gastos Operativos Generales'!D10 -> 8400 | D10: 0.16 | E10: Publicidad, hosting y dominio
C11: =SUM(C6:C10) -> 52500 | D11: =SUM(D6:D10) -> 1

Sheet Reserva Estratégica
B1: Presupuesto Reserva Estratégica "Four Js"
B5: Concepto | C5: Monto (USD) | D5: % del Depto. | E5: Descripción
B6: Fondo para imprevistos | C6: =Global!C$9*'Reserva Estratégica'!D6 -> 20250 | D6: 0.27 | E6: Cobertura ante fallas críticas, contingencias legales, o sustitución de equipos.
B7: Innovación y proyectos piloto | C7: =Global!C$9*'Reserva Estratégica'!D7 -> 17250 | D7: 0.23 | E7: Investigación de nuevas tecnologías, pruebas de concepto, y desarrollo experimental.
B8: Infraestructura tecnica | C8: =Global!C$9*'Reserva Estratégica'!D8 -> 15000 | D8: 0.2 | E8: Ampliación o actualización de servidores, licencias o entornos de nube.
B9: Capacitación avanzada y certificaciones estratégicas | C9: =Global!C$9*'Reserva Estratégica'!D9 -> 12750 | D9: 0.17 | E9: Entrenamiento de alto nivel, certificaciones internacionales, o cursos técnicos clave.
B10: Fondo de expansión o alianzas estratégicas | C10: =Global!C$9*'Reserva Estratégica'!D10 -> 9750 | D10: 0.13 | E10: Soporte para colaboraciones, expansión regional o proyectos conjuntos.
C11: =SUM(C6:C10) -> 75000 | D11: =SUM(D6:D10) -> 1
