Workbook

Sheet 1.-Históricos
B2: Cliente: | C2: Nombre del cliente
B3: Proyecto: | C3: Nombre del proyecto
B6: Información histórica de referencia
B7: Indique el nombre del proyecto o proyectos de referencia revisados
B8: Nombre del proyecto | F8: Aspectos considerados
B9: Proyecto de Referencia 1
B10: Proyecto de Referencia 2
B11: Proyecto de Referencia 3
B12: Proyecto de Referencia 4
B16: Secuencia Fibonacci
B17: 0 + 1 | C17: 1 | D17: Fácil
B18: 1 + 1 | C18: 2
B19: 1 + 2 | C19: 3
B20: 2 + 3 | C20: 5
B21: 3 + 5 | C21: 8
B22: 5 + 8 | C22: 13
B23: 8 + 13 | C23: 21
B24: 13 + 21 | C24: 34
B25: 21 + 34 | C25: 55
B26: 34 + 55 | C26: 89
B27: 55 + 89 | C27: 144 | D27: Díficil

Sheet 2.-Round 1
A1: Tabla de estimación (round 1)
B2: Desviación estandar aceptada: <= 10%
A3: Identificador | B3: Enunciado de historia | C3: Prioridad | D3: Tamaño esperado | M3: Observaciones
D4: Estimador 1 | E4: Estimador 2 | F4: Estimador 3 | G4: Sprint | H4: Maximo | I4: Valor medio | J4: Minimo | K4: desviación (%) | L4: ¿Se acepta?
A5: xxxx-xxxx-xxx1 | B5: Como un [vendedor], necesito [ver el historial de compras del cliente], con la finalidad de [ofrecerle productos relacionados] | C5: Media | D5: 3 | E5: 8 | F5: 5 | G5: 1 | H5: =MAX(D5:G5) -> 8 | I5: =IF(SUM(D5:F5)<>0,AVERAGE(D5:F5),0) -> 5.3333333 | J5: =MIN(D5:F5) -> 3 | K5: =IF(I5<>0,MAX((H5-I5)/I5*100%,(I5-J5)/I5*100%),0) -> 0.5 | L5: No | M5: Se coincide que tiene un grado de dificultad bajo pero aun no se ponen de acuerdo el nivel de dificultad.
A6: xxxx-xxxx-xxx2 | B6: Como un [vendedor], necesito [ver el inventario en tiempo real], con la finalidad de [ofrecer productos que estén disponibles] | C6: Media | D6: 5 | E6: 13 | F6: 8 | G6: 2 | H6: =MAX(D6:G6) -> 13 | I6: =IF(SUM(D6:F6)<>0,AVERAGE(D6:F6),0) -> 8.6666667 | J6: =MIN(D6:F6) -> 5 | K6: =IF(I6<>0,MAX((H6-I6)/I6*100%,(I6-J6)/I6*100%),0) -> 0.5 | L6: No | M6: Modificar el inventario en tiempo real involucra difícultades de red para los usuarios al momento de actualizar.
A7: xxxx-xxxx-xxx3 | B7: Como un [vendedor], necesito [ver el historial de precios del producto], con la finalidad de [ofrecer precios competitivos] | C7: Baja | D7: 3 | E7: 3 | F7: 3 | G7: 3 | H7: =MAX(D7:F7) -> 3 | I7: =IF(SUM(D7:F7)<>0,AVERAGE(D7:F7),0) -> 3 | J7: =MIN(D7:F7) -> 3 | K7: =IF(I7<>0,MAX((H7-I7)/I7*100%,(I7-J7)/I7*100%),0) -> 0 | L7: Yes | M7: N/A
A8: xxxx-xxxx-xxx4 | B8: Como un [vendedor], necesito [metricas de ventas], con la finalidad de [identificar productos más vendidos] | C8: Alta | D8: 8 | E8: 3 | F8: 5 | G8: 1 | H8: =MAX(D8:G8) -> 8 | I8: =IF(SUM(D8:F8)<>0,AVERAGE(D8:F8),0) -> 5.3333333 | J8: =MIN(D8:F8) -> 3 | K8: =IF(I8<>0,MAX((H8-I8)/I8*100%,(I8-J8)/I8*100%),0) -> 0.5 | L8: No | M8: No se llegó a un acuerdo por parte de los estimadores, ya que uno dice que se tiene historial con esa programación y otro que es más complejo de lo que parece por la lectura de los datos de ventas registrados.
A9: xxxx-xxxx-xxx5 | B9: Como un [vendedor], necesito [ver historial de devoluciones por producto], con la finalidad de [identificar produtos más defectuosos] | C9: Media | D9: 8 | E9: 8 | F9: 8 | G9: 3 | H9: =MAX(D9:F9) -> 8 | I9: =IF(SUM(D9:F9)<>0,AVERAGE(D9:F9),0) -> 8 | J9: =MIN(D9:F9) -> 8 | K9: =IF(I9<>0,MAX((H9-I9)/I9*100%,(I9-J9)/I9*100%),0) -> 0 | L9: Yes | M9: N/A
A10: xxxx-xxxx-xxx6 | B10: Como un [vendedor], necesito [enviar correos o whatsapps personalizados a los clientes], con la finalidad de [reforzar en contacto con clientes potenciales] | C10: Baja | D10: 8 | E10: 21 | F10: 13 | G10: 3 | H10: =MAX(D10:G10) -> 21 | I10: =IF(SUM(D10:F10)<>0,AVERAGE(D10:F10),0) -> 14 | J10: =MIN(D10:F10) -> 8 | K10: =IF(I10<>0,MAX((H10-I10)/I10*100%,(I10-J10)/I10*100%),0) -> 0.5 | L10: No | M10: No se llegó a un acuerdo po rparte de los estimadores porque el estimador 3 menciona la díficultad que implica conectarse con whatsapp y el respaldo de las converzaciones.
A11: xxxx-xxxx-xxx7 | B11: Como un [administrador], necesito [otorgar permisos para acceder a la información de nuestros clientes], con la finalidad de [preservar la seguridad de la información de nuestros clientes] | C11: Alta | D11: 13 | E11: 13 | F11: 13 | G11: 2 | H11: =MAX(D11:G11) -> 13 | I11: =IF(SUM(D11:F11)<>0,AVERAGE(D11:F11),0) -> 13 | J11: =MIN(D11:F11) -> 13 | K11: =IF(I11<>0,MAX((H11-I11)/I11*100%,(I11-J11)/I11*100%),0) -> 0 | L11: Yes | M11: N/A
A12: xxxx-xxxx-xxx8 | B12: Como un [Cliente], necesito [agregar al carrito los productos que quiero], con la finalidad de [comprar varios productos al mismo tiempo] | C12: Alta | D12: 21 | E12: 13 | F12: 8 | G12: 2 | H12: =MAX(D12:G12) -> 21 | I12: =IF(SUM(D12:F12)<>0,AVERAGE(D12:F12),0) -> 14 | J12: =MIN(D12:F12) -> 8 | K12: =IF(I12<>0,MAX((H12-I12)/I12*100%,(I12-J12)/I12*100%),0) -> 0.5 | L12: No | M12: Se conocen los elementos necesarios, pero al no conocer la cantidad exacta de elementos de credito que se puede otorgar al cliente no se a llegado a un acuerdo por parte del estimador 3
A13: xxxx-xxxx-xxx9 | B13: Como un [cliente], necesito [registrar mis datos de facturación], con la finalidad de [resivir mis facturas en el correo electrónico] | C13: Alta | D13: 8 | E13: 8 | F13: 8 | G13: 1 | H13: =MAX(D13:G13) -> 8 | I13: =IF(SUM(D13:F13)<>0,AVERAGE(D13:F13),0) -> 8 | J13: =MIN(D13:F13) -> 8 | K13: =IF(I13<>0,MAX((H13-I13)/I13*100%,(I13-J13)/I13*100%),0) -> 0 | L13: Yes | M13: N/A
A14: xxxx-xxxx-xxx10 | B14: Como un [responsable de envios], necesito [poder informar el estado del producto una vez enviado], con la finalidad de [mantener informado al cliente] | C14: Media | D14: 5 | E14: 5 | F14: 2 | G14: 1 | H14: =MAX(D14:G14) -> 5 | I14: =IF(SUM(D14:F14)<>0,AVERAGE(D14:F14),0) -> 4 | J14: =MIN(D14:F14) -> 2 | K14: =IF(I14<>0,MAX((H14-I14)/I14*100%,(I14-J14)/I14*100%),0) -> 0.5 | L14: No | M14: Todos coinciden que es simple pero no en qué tán simple es.

Sheet 3.-Round 2
A1: Tabla de estimación (round 2)
B2: Desviación estandar aceptada: <= 10%
A3: Identificador | B3: Enunciado de historia | C3: Prioridad | D3: Tamaño esperado | M3: Observaciones
D4: Estimador 1 | E4: Estimador 2 | F4: Estimador 3 | G4: Sprint | H4: Maximo | I4: Valor medio | J4: Minimo | K4: desviación (%) | L4: ¿Se acepta?
A5: xxxx-xxxx-xxx1 | B5: Como un [vendedor], necesito [ver el historial de compras del cliente], con la finalidad de [ofrecerle productos relacionados] | C5: Media | D5: 5 | E5: 5 | F5: 5 | G5: 1 | H5: =MAX(D5:G5) -> 5 | I5: =IF(SUM(D5:F5)<>0,AVERAGE(D5:F5),0) -> 5 | J5: =MIN(D5:F5) -> 5 | K5: =IF(I5<>0,MAX((H5-I5)/I5*100%,(I5-J5)/I5*100%),0) -> 0 | L5: Yes | M5: N/A
A6: xxxx-xxxx-xxx2 | B6: Como un [vendedor], necesito [ver el inventario en tiempo real], con la finalidad de [ofrecer productos que estén disponibles] | C6: Media | D6: 5 | E6: 13 | F6: 8 | G6: 2 | H6: =MAX(D6:G6) -> 13 | I6: =IF(SUM(D6:F6)<>0,AVERAGE(D6:F6),0) -> 8.6666667 | J6: =MIN(D6:F6) -> 5 | K6: =IF(I6<>0,MAX((H6-I6)/I6*100%,(I6-J6)/I6*100%),0) -> 0.5 | L6: No | M6: Dos estimadores estan de acuerdo pero el 3ro menciona que la actualización sigue siendo un factor que no se esta concideranro detenidamente.
A7: xxxx-xxxx-xxx3 | B7: Como un [vendedor], necesito [ver el historial de precios del producto], con la finalidad de [ofrecer precios competitivos] | C7: Baja | D7: 3 | E7: 3 | F7: 3 | G7: 3 | H7: =MAX(D7:F7) -> 3 | I7: =IF(SUM(D7:F7)<>0,AVERAGE(D7:F7),0) -> 3 | J7: =MIN(D7:F7) -> 3 | K7: =IF(I7<>0,MAX((H7-I7)/I7*100%,(I7-J7)/I7*100%),0) -> 0 | L7: Yes | M7: N/A
A8: xxxx-xxxx-xxx4 | B8: Como un [vendedor], necesito [metricas de ventas], con la finalidad de [identificar productos más vendidos] | C8: Alta | D8: 8 | E8: 8 | F8: 8 | G8: 1 | H8: =MAX(D8:G8) -> 8 | I8: =IF(SUM(D8:F8)<>0,AVERAGE(D8:F8),0) -> 8 | J8: =MIN(D8:F8) -> 8 | K8: =IF(I8<>0,MAX((H8-I8)/I8*100%,(I8-J8)/I8*100%),0) -> 0 | L8: Yes | M8: N/A
A9: xxxx-xxxx-xxx5 | B9: Como un [vendedor], necesito [ver historial de devoluciones por producto], con la finalidad de [identificar produtos más defectuosos] | C9: Media | D9: 8 | E9: 8 | F9: 8 | G9: 3 | H9: =MAX(D9:F9) -> 8 | I9: =IF(SUM(D9:F9)<>0,AVERAGE(D9:F9),0) -> 8 | J9: =MIN(D9:F9) -> 8 | K9: =IF(I9<>0,MAX((H9-I9)/I9*100%,(I9-J9)/I9*100%),0) -> 0 | L9: Yes | M9: N/A
A10: xxxx-xxxx-xxx6 | B10: Como un [vendedor], necesito [enviar correos o whatsapps personalizados a los clientes], con la finalidad de [reforzar en contacto con clientes potenciales] | C10: Baja | D10: 13 | E10: 13 | F10: 13 | G10: 3 | H10: =MAX(D10:G10) -> 13 | I10: =IF(SUM(D10:F10)<>0,AVERAGE(D10:F10),0) -> 13 | J10: =MIN(D10:F10) -> 13 | K10: =IF(I10<>0,MAX((H10-I10)/I10*100%,(I10-J10)/I10*100%),0) -> 0 | L10: Yes | M10: N/A
A11: xxxx-xxxx-xxx7 | B11: Como un [administrador], necesito [otorgar permisos para acceder a la información de nuestros clientes], con la finalidad de [preservar la seguridad de la información de nuestros clientes] | C11: Alta | D11: 13 | E11: 13 | F11: 13 | G11: 2 | H11: =MAX(D11:G11) -> 13 | I11: =IF(SUM(D11:F11)<>0,AVERAGE(D11:F11),0) -> 13 | J11: =MIN(D11:F11) -> 13 | K11: =IF(I11<>0,MAX((H11-I11)/I11*100%,(I11-J11)/I11*100%),0) -> 0 | L11: Yes | M11: N/A
A12: xxxx-xxxx-xxx8 | B12: Como un [Cliente], necesito [agregar al carrito los productos que quiero], con la finalidad de [comprar varios productos al mismo tiempo] | C12: Alta | D12: 21 | E12: 13 | F12: 8 | G12: 2 | H12: =MAX(D12:G12) -> 21 | I12: =IF(SUM(D12:F12)<>0,AVERAGE(D12:F12),0) -> 14 | J12: =MIN(D12:F12) -> 8 | K12: =IF(I12<>0,MAX((H12-I12)/I12*100%,(I12-J12)/I12*100%),0) -> 0.5 | L12: No | M12: Se conocen los elementos necesarios, pero al no conocer la cantidad exacta de elementos de credito que se puede otorgar al cliente no se a llegado a un acuerdo por parte del estimador 3
A13: xxxx-xxxx-xxx9 | B13: Como un [cliente], necesito [registrar mis datos de facturación], con la finalidad de [resivir mis facturas en el correo electrónico] | C13: Alta | D13: 8 | E13: 8 | F13: 8 | G13: 1 | H13: =MAX(D13:G13) -> 8 | I13: =IF(SUM(D13:F13)<>0,AVERAGE(D13:F13),0) -> 8 | J13: =MIN(D13:F13) -> 8 | K13: =IF(I13<>0,MAX((H13-I13)/I13*100%,(I13-J13)/I13*100%),0) -> 0 | L13: Yes | M13: N/A
A14: xxxx-xxxx-xxx10 | B14: Como un [responsable de envios], necesito [poder informar el estado del producto una vez enviado], con la finalidad de [mantener informado al cliente] | C14: Media | D14: 5 | E14: 5 | F14: 5 | G14: 1 | H14: =MAX(D14:G14) -> 5 | I14: =IF(SUM(D14:F14)<>0,AVERAGE(D14:F14),0) -> 5 | J14: =MIN(D14:F14) -> 5 | K14: =IF(I14<>0,MAX((H14-I14)/I14*100%,(I14-J14)/I14*100%),0) -> 0 | L14: Yes | M14: N/A

Sheet 4.-Round 3
A4: Tabla de estimación (round 3)
B5: Desviación estandar aceptada: <= 10%
A6: Identificador | B6: Enunciado de historia | C6: Prioridad | D6: Tamaño esperado | M6: Observaciones
D7: Estimador 1 | E7: Estimador 2 | F7: Estimador 3 | G7: Sprint | H7: Maximo | I7: Valor medio | J7: Minimo | K7: desviación (%) | L7: ¿Se acepta? | O7: Calificación por sprint | R7: 1 | S7: 2 | T7: 3
A8: xxxx-xxxx-xxx1 | B8: Como un [vendedor], necesito [ver el historial de compras del cliente], con la finalidad de [ofrecerle productos relacionados] | C8: Media | D8: 5 | E8: 5 | F8: 5 | G8: 1 | H8: =MAX(D8:G8) -> 5 | I8: =IF(SUM(D8:F8)<>0,AVERAGE(D8:F8),0) -> 5 | J8: =MIN(D8:F8) -> 5 | K8: =IF(I8<>0,MAX((H8-I8)/I8*100%,(I8-J8)/I8*100%),0) -> 0 | L8: Yes | M8: N/A | R8: =5+8+8+5 -> 26 | S8: =13+5+8 -> 26 | T8: =3+8+13 -> 24
A9: xxxx-xxxx-xxx2 | B9: Como un [vendedor], necesito [ver el inventario en tiempo real], con la finalidad de [ofrecer productos que estén disponibles] | C9: Media | D9: 13 | E9: 13 | F9: 13 | G9: 2 | H9: =MAX(D9:G9) -> 13 | I9: =IF(SUM(D9:F9)<>0,AVERAGE(D9:F9),0) -> 13 | J9: =MIN(D9:F9) -> 13 | K9: =IF(I9<>0,MAX((H9-I9)/I9*100%,(I9-J9)/I9*100%),0) -> 0 | L9: Yes | M9: Dos estimadores estan de acuerdo pero el 3ro menciona que la actualización sigue siendo un factor que no se esta concideranro detenidamente.
A10: xxxx-xxxx-xxx3 | B10: Como un [vendedor], necesito [ver el historial de precios del producto], con la finalidad de [ofrecer precios competitivos] | C10: Baja | D10: 3 | E10: 3 | F10: 3 | G10: 3 | H10: 1 | I10: =IF(SUM(D10:F10)<>0,AVERAGE(D10:F10),0) -> 3 | J10: =MIN(D10:F10) -> 3 | K10: =IF(I10<>0,MAX((H10-I10)/I10*100%,(I10-J10)/I10*100%),0) -> 0 | L10: Yes | M10: N/A
A11: xxxx-xxxx-xxx4 | B11: Como un [vendedor], necesito [metricas de ventas], con la finalidad de [identificar productos más vendidos] | C11: Alta | D11: 8 | E11: 8 | F11: 8 | G11: 1 | H11: =MAX(D11:G11) -> 8 | I11: =IF(SUM(D11:F11)<>0,AVERAGE(D11:F11),0) -> 8 | J11: =MIN(D11:F11) -> 8 | K11: =IF(I11<>0,MAX((H11-I11)/I11*100%,(I11-J11)/I11*100%),0) -> 0 | L11: Yes | M11: N/A
A12: xxxx-xxxx-xxx5 | B12: Como un [vendedor], necesito [ver historial de devoluciones por producto], con la finalidad de [identificar produtos más defectuosos] | C12: Media | D12: 8 | E12: 8 | F12: 8 | G12: 3 | H12: 2 | I12: =IF(SUM(D12:F12)<>0,AVERAGE(D12:F12),0) -> 8 | J12: =MIN(D12:F12) -> 8 | K12: =IF(I12<>0,MAX((H12-I12)/I12*100%,(I12-J12)/I12*100%),0) -> 0 | L12: Yes | M12: N/A
A13: xxxx-xxxx-xxx6 | B13: Como un [vendedor], necesito [enviar correos o whatsapps personalizados a los clientes], con la finalidad de [reforzar en contacto con clientes potenciales] | C13: Baja | D13: 13 | E13: 13 | F13: 13 | G13: 3 | H13: =MAX(D13:G13) -> 13 | I13: =IF(SUM(D13:F13)<>0,AVERAGE(D13:F13),0) -> 13 | J13: =MIN(D13:F13) -> 13 | K13: =IF(I13<>0,MAX((H13-I13)/I13*100%,(I13-J13)/I13*100%),0) -> 0 | L13: Yes | M13: N/A
A14: xxxx-xxxx-xxx7 | B14: Como un [administrador], necesito [otorgar permisos para acceder a la información de nuestros clientes], con la finalidad de [preservar la seguridad de la información de nuestros clientes] | C14: Alta | D14: 5 | E14: 5 | F14: 5 | G14: 2 | H14: =MAX(D14:G14) -> 5 | I14: =IF(SUM(D14:F14)<>0,AVERAGE(D14:F14),0) -> 5 | J14: =MIN(D14:F14) -> 5 | K14: =IF(I14<>0,MAX((H14-I14)/I14*100%,(I14-J14)/I14*100%),0) -> 0 | L14: Yes | M14: N/A
A15: xxxx-xxxx-xxx8 | B15: Como un [Cliente], necesito [agregar al carrito los productos que quiero], con la finalidad de [comprar varios productos al mismo tiempo] | C15: Alta | D15: 8 | E15: 8 | F15: 5 | G15: 2 | H15: =MAX(D15:G15) -> 8 | I15: =IF(SUM(D15:F15)<>0,AVERAGE(D15:F15),0) -> 7 | J15: =MIN(D15:F15) -> 5 | K15: =IF(I15<>0,MAX((H15-I15)/I15*100%,(I15-J15)/I15*100%),0) -> 0.28571429 | L15: No | M15: No se llego a un acuerdo, pero se considerarán 5 pts por ser el número más alto.
A16: xxxx-xxxx-xxx9 | B16: Como un [cliente], necesito [registrar mis datos de facturación], con la finalidad de [resivir mis facturas en el correo electrónico] | C16: Alta | D16: 8 | E16: 8 | F16: 8 | G16: 1 | H16: =MAX(D16:G16) -> 8 | I16: =IF(SUM(D16:F16)<>0,AVERAGE(D16:F16),0) -> 8 | J16: =MIN(D16:F16) -> 8 | K16: =IF(I16<>0,MAX((H16-I16)/I16*100%,(I16-J16)/I16*100%),0) -> 0 | L16: Yes | M16: N/A
A17: xxxx-xxxx-xxx10 | B17: Como un [responsable de envios], necesito [poder informar el estado del producto una vez enviado], con la finalidad de [mantener informado al cliente] | C17: Media | D17: 5 | E17: 5 | F17: 5 | G17: 1 | H17: =MAX(D17:G17) -> 5 | I17: =IF(SUM(D17:F17)<>0,AVERAGE(D17:F17),0) -> 5 | J17: =MIN(D17:F17) -> 5 | K17: =IF(I17<>0,MAX((H17-I17)/I17*100%,(I17-J17)/I17*100%),0) -> 0 | L17: Yes | M17: N/A
A18: Sumatoría de Tamaño esperado | D18: =SUM(D8:D17) -> 76 | E18: =SUM(E8:E17) -> 76 | F18: =SUM(F8:F17) -> 73

Sheet 5.-Resumen estimación de tamaño
A2: Resumen
A3: Pivote | B3: Actualizaciones online en base de datos de manera instantanea | E3: Ejemplo: 8 pts.de historia
A4: Equipo | B4: 28 pts por sprint. | E4: El sprint 2 y 3 nos dan margen de error indirectametne.
A5: Sprint | B5: PHU | C5: Total puntos
A6: 1 | B6: ='4.-Round 3'!R8 -> 26 | C6: =SUM(B6:B8) -> 76
A7: 2 | B7: ='4.-Round 3'!S8 -> 26
A8: 3 | B8: ='4.-Round 3'!T8 -> 24
A10: Puntos totales | B10: ='4.-Round 3'!D18 -> 76 | C10: ='4.-Round 3'!E18 -> 76 | D10: ='4.-Round 3'!F18 -> 73
A11: Resultado Tamaño | B11: =MAX(B10:D10) -> 76
A14: Tablas de datos
A15: Lenguaje | B15: Horas PF promedio
A16: Java | B16: 6
A18: RESULTADO
A19: Estimación→ | B19: Esfuerzo | C19: =B16*B11 -> 456 | D19: hrs

Sheet 6.-Estimación esfuerzo y costo
B2: Desglose de horas por actividad
B3: Actividades | E3: Horas | F3: % | G3: Días hombre
B4: Análisis | E4: =E6*F4 -> 91.2 | F4: 0.2 | G4: =E4/$D12 -> 15.2
B5: Diseño | E5: =E6*F5 -> 91.2 | F5: 0.2 | G5: =E5/$D12 -> 15.2
B6: Construcción | E6: ='5.-Resumen estimación de tamaño'!C19 -> 456 | F6: 0.4 | G6: =E6/$D12 -> 76
B7: Pruebas | E7: =E6*F7 -> 91.2 | F7: 0.2 | G7: =E7/$D12 -> 15.2
B9: Total | E9: =SUM(E4:E7) -> 729.6 | F9: =SUM(F4:F7) -> 1 | G9: =SUM(G4:G7) -> 121.6
B11: DPM | D11: Horas efectivas de trabajo | F11: Días totales (red) | H11: Plazo en meses
B12: 21.5 | D12: 6 | F12: =ROUNDUP(G9,0) -> 122 | H12: =ROUNDUP((G9/B12),0) -> 6
B14: Costos
B15: Rol | D15: Costo por mes
B16: Líder de proyecto | D16: 100
B17: Líder técnico | C17: LT | D17: 200
B18: Analista | C18: AN | D18: 100
B19: Arquitecto | C19: AR | D19: 100
B20: Desarrollador | D20: 200
B21: Tester | C21: DE | D21: 300
B22: Total | D22: =SUM(D16:D21)*H12 -> 6000
B24: Otros conceptos
B25: Conceptos | E25: Costo
B26: Compras | E26: 100
B27: Licencias | E27: 200
B28: Formación | E28: 1000
B29: Consumibles | E29: 120
B31: Total | E31: =SUM(E26:E30) -> 1420
C33: Presupuesto total | E33: =D22+E31 -> 7420
C36: Análisis | E36: Razonamiento o base para la estimación y motivo de ajuste en la estimación. Describir el fundamento de las estimaciones de esfuerzo, duración y costo, para que proporcionen el contexto para el uso de datos históricos.

Sheet Lista
B1: Prioridad
B2: Alta
B3: Media
B4: Baja
